main.py
mynewproject_this_is_unique-0.1.0.dist-info/METADATA
mynewproject_this_is_unique-0.1.0.dist-info/WHEEL
mynewproject_this_is_unique-0.1.0.dist-info/top_level.txt
mynewproject_this_is_unique-0.1.0.dist-info/RECORD
