Metadata-Version: 2.4
Name: mynewproject-this-is-unique
Version: 0.1.0
Summary: Add your description here
Requires-Python: >=3.10
Requires-Dist: requests>=2.32.3
